pyAtoM/__init__.py
pyAtoM/api.py
pyatom-0.4.1.dist-info/LICENSE
pyatom-0.4.1.dist-info/METADATA
pyatom-0.4.1.dist-info/WHEEL
pyatom-0.4.1.dist-info/top_level.txt
pyatom-0.4.1.dist-info/RECORD
