Metadata-Version: 2.2
Name: pyAtoM
Version: 0.4.1
Summary: Python library for the AtoM archival description and access platform API
Home-page: 
Author: James Carr
Author-email: drjamescarr@gmail.com
License: Apache License 2.0
Project-URL: Documentation, https://github.com/carj/pyAtoM
Project-URL: Source, https://github.com/carj/pyAtoM
Project-URL: Discussion Forum, https://github.com/carj/pyAtoM/discussions
Keywords: API Preservation
Classifier: Programming Language :: Python :: 3
Classifier: Programming Language :: Python :: 3.8
Classifier: Programming Language :: Python :: 3.9
Classifier: Programming Language :: Python :: 3.10
Classifier: Programming Language :: Python :: 3.11
Classifier: Programming Language :: Python :: 3.12
Classifier: License :: OSI Approved :: Apache Software License
Classifier: Operating System :: OS Independent
Classifier: Topic :: System :: Archiving
License-File: LICENSE
Requires-Dist: requests
Requires-Dist: urllib3
Requires-Dist: certifi
Dynamic: author
Dynamic: author-email
Dynamic: classifier
Dynamic: description
Dynamic: description-content-type
Dynamic: keywords
Dynamic: license
Dynamic: project-url
Dynamic: requires-dist
Dynamic: summary
